toraniko/__init__.py
toraniko/math.py
toraniko/model.py
toraniko/styles.py
toraniko/utils.py
toraniko/tests/__init__.py
toraniko/tests/test_math.py
toraniko/tests/test_model.py
toraniko/tests/test_utils.py
toraniko-1.1.1.dist-info/LICENSE
toraniko-1.1.1.dist-info/METADATA
toraniko-1.1.1.dist-info/WHEEL
toraniko-1.1.1.dist-info/top_level.txt
toraniko-1.1.1.dist-info/RECORD
