Metadata-Version: 2.1
Name: toraniko
Version: 1.1.1
License-File: LICENSE
Requires-Dist: numpy ~=1.26.2
Requires-Dist: polars ~=1.0
